[1,["70Yotum5tGPqw7ggE+SEpY@f9941","d8ug8A8ERNyqovoQSG7mQo@f9941","c4vC2nzERB1qyMWd8+LZfq@f9941","e6XPJwMEBOmLpwddQLRA3x","12cKZkyblNg7sffmJRn2tK@6c48a","1d+Uyg3LhN1oVlxuUCzylt@6c48a","35jrWbDkVO3puNVxNsXj77@6c48a","658eojStNOd6nIrLikWnPl@f9941","35jrWbDkVO3puNVxNsXj77@f9941","f0xgQVHcZCOpbAR/vK2ocX@f9941","73M9bYiVpHepFNmgW22q3I@f9941","12cKZkyblNg7sffmJRn2tK@f9941","1d+Uyg3LhN1oVlxuUCzylt@f9941","658eojStNOd6nIrLikWnPl@6c48a","70Yotum5tGPqw7ggE+SEpY@6c48a","73M9bYiVpHepFNmgW22q3I@6c48a","c4vC2nzERB1qyMWd8+LZfq@6c48a","d8ug8A8ERNyqovoQSG7mQo@6c48a","f0xgQVHcZCOpbAR/vK2ocX@6c48a"],["node","_spriteFrame","_textureSource","root","data","_defaultClip"],["cc.SpriteFrame",["cc.Node",["_name","_layer","_components","_prefab","_parent","_lpos","_children","_lrot","_euler","_lscale"],1,9,4,1,5,2,5,5,5],["cc.UITransform",["node","__prefab","_contentSize","_anchorPoint"],3,1,4,5,5],["cc.Prefab",["_name"],2],["cc.CompPrefabInfo",["fileId"],2],["cc.Animation",["playOnLoad","node","__prefab","_clips","_defaultClip"],2,1,4,3,6],["cc.PrefabInfo",["fileId","instance","targetOverrides","nestedPrefabInstanceRoots","root","asset"],-1,1,1],["cc.Sprite",["node","__prefab","_spriteFrame"],3,1,4,6]],[[4,0,2],[6,0,1,2,3,4,5,5],[7,0,1,2,1],[1,0,1,4,2,3,5,3],[2,0,1,2,1],[2,0,1,2,3,1],[1,0,1,4,2,3,3],[2,0,1,1],[1,0,1,4,6,2,3,5,3],[3,0,2],[1,0,1,6,2,3,3],[1,0,1,4,2,3,5,7,8,3],[1,0,1,4,2,3,5,7,9,8,3],[5,0,1,2,3,4,2]],[[[{"name":"icon-08","rect":{"x":0,"y":0,"width":20,"height":10},"offset":{"x":0,"y":0},"originalSize":{"width":20,"height":10},"rotated":false,"capInsets":[0,0,0,0],"vertices":{"rawPosition":[-10,-5,0,10,-5,0,-10,5,0,10,5,0],"indexes":[0,1,2,2,1,3],"uv":[0,10,20,10,0,0,20,0],"nuv":[0,0,1,0,0,1,1,1],"minPos":{"x":-10,"y":-5,"z":0},"maxPos":{"x":10,"y":5,"z":0}},"packable":true,"pixelsToUnit":100,"pivot":{"x":0.5,"y":0.5},"meshType":0}],[0],0,[0],[2],[4]],[[{"name":"icon-09","rect":{"x":0,"y":0,"width":20,"height":10},"offset":{"x":0,"y":0},"originalSize":{"width":20,"height":10},"rotated":false,"capInsets":[0,0,0,0],"vertices":{"rawPosition":[-10,-5,0,10,-5,0,-10,5,0,10,5,0],"indexes":[0,1,2,2,1,3],"uv":[0,10,20,10,0,0,20,0],"nuv":[0,0,1,0,0,1,1,1],"minPos":{"x":-10,"y":-5,"z":0},"maxPos":{"x":10,"y":5,"z":0}},"packable":true,"pixelsToUnit":100,"pivot":{"x":0.5,"y":0.5},"meshType":0}],[0],0,[0],[2],[5]],[[{"name":"icon-04","rect":{"x":0,"y":0,"width":29,"height":28},"offset":{"x":0,"y":0},"originalSize":{"width":29,"height":28},"rotated":false,"capInsets":[0,0,0,0],"vertices":{"rawPosition":[-14.5,-14,0,14.5,-14,0,-14.5,14,0,14.5,14,0],"indexes":[0,1,2,2,1,3],"uv":[0,28,29,28,0,0,29,0],"nuv":[0,0,1,0,0,1,1,1],"minPos":{"x":-14.5,"y":-14,"z":0},"maxPos":{"x":14.5,"y":14,"z":0}},"packable":true,"pixelsToUnit":100,"pivot":{"x":0.5,"y":0.5},"meshType":0}],[0],0,[0],[2],[6]],[[[9,"per_sheep"],[10,"per_sheep",33554432,[-4,-5],[[7,-2,[0,"52ZyF7OmhFL7BFAwiztNfj"]],[13,true,-3,[0,"8c1ZNBEPpPnagpjmNfb86X"],[14],15]],[1,"55g0bUrBhChLGvX93iEdci",null,null,null,-1,0]],[8,"sheep_all",33554432,1,[-7,-8,-9,-10,-11,-12,-13],[[7,-6,[0,"8aZ3jHkopHRbDC1d0cB/Ol"]]],[1,"cerV0qjwxMm4kTRUzFBsTf",null,null,null,1,0],[1,0,70,0]],[8,"head",33554432,2,[-15,-16,-17,-18,-19,-20,-21],[[7,-14,[0,"4aek2j/IxAhoLoqkwPJiAl"]]],[1,"f12Jr/nPxH9auXVEAYSYNX",null,null,null,1,0],[1,-58.993,20.36,0]],[6,"sheep_shadow",33554432,1,[[4,-22,[0,"c0J6a2DnVHTbEtqNwJxqkl"],[5,134,28]],[2,-23,[0,"cbGmn/BkRAyoiIAGNTvU9z"],0]],[1,"14bw0yK0ZLaLPg+nbOE+vv",null,null,null,1,0]],[3,"tui-qian-1",33554432,2,[[5,-24,[0,"bbb9WHYJZFmKeeY870tGnl"],[5,18,31],[0,0.5,0.8]],[2,-25,[0,"f6pOXMl7BBbpZWGhc/IXIt"],1]],[1,"a7vLepPr5ME6GcZjDWRFD2",null,null,null,1,0],[1,-39.676,-36.588,0]],[3,"weiba",33554432,2,[[4,-26,[0,"552cTAqThOVLjhXu4Flxxo"],[5,29,28]],[2,-27,[0,"23/E/3PMpDiZDBKTHpQhkU"],2]],[1,"bfmM0ijc5IE6he6nFLHcTI",null,null,null,1,0],[1,69.866,17.085,0]],[3,"tui-hou-1",33554432,2,[[5,-28,[0,"58MmYoMq5PM6MFnl5NNvYT"],[5,18,31],[0,0.5,0.8]],[2,-29,[0,"03GMIbcglA3qY1cmIWm3XS"],3]],[1,"e9ckYXIyRB3KGQYOyMlKjv",null,null,null,1,0],[1,14.618,-39.72,0]],[6,"body",33554432,2,[[4,-30,[0,"bczSxfWTZMp6GcoMB+fXj1"],[5,139,106]],[2,-31,[0,"aeOT79dg9Nn7yVyVg5p4Hs"],4]],[1,"e1F3IdoA5Pw5qKsk5dysYD",null,null,null,1,0]],[3,"tui-qian-2",33554432,2,[[5,-32,[0,"85ZsDxdwpDu6EydQsTF5sX"],[5,18,31],[0,0.5,0.8]],[2,-33,[0,"54e7gSzadAYZQqelpxDT0y"],5]],[1,"67JrtC48tClbu0OBmsWzhI",null,null,null,1,0],[1,-24.016,-40.765,0]],[11,"tui-hou-2",33554432,2,[[5,-34,[0,"23Gy3/vHtCW5w0vZve5ywZ"],[5,18,31],[0,0.5,0.8]],[2,-35,[0,"fbiYzsfcFFb5i7vqH8QTAl"],6]],[1,"cdweDAKe5D2ZOwEm+T2ik8",null,null,null,1,0],[1,28.037,-41.734,0],[3,0,0,0.09931974974363901,0.9950555699612263],[1,0,0,11.4]],[3,"rr",33554432,3,[[5,-36,[0,"7c7jmdWjRO5ZkclRGYj5ok"],[5,29,46],[0,0.3,0.8]],[2,-37,[0,"97cr4HrA5Ce4XrXSXliNGP"],7]],[1,"14/mxcC5tMzbdIZOV8YqkQ",null,null,null,1,0],[1,22.971,-3.132,0]],[12,"ll",33554432,3,[[5,-38,[0,"a2BQzRsX1LbKvjh70r06A9"],[5,29,46],[0,0.3,0.8]],[2,-39,[0,"deS7kVxvBGwbAyuG6mU4JZ"],8]],[1,"c0Kq97oA5BWp9syWq3eNya",null,null,null,1,0],[1,-27.927,2.422,0],[3,0,0,-0.15643446504023087,0.9876883405951378],[1,-1,1,1],[1,0,0,-18]],[6,"main",33554432,3,[[4,-40,[0,"76le495D9DRKDejdD6U6/t"],[5,59,80]],[2,-41,[0,"55LL6hVe9EK7n6oQvz4mWh"],9]],[1,"43X03HwWlLzqJohzqKXbv1",null,null,null,1,0]],[3,"meimao-2",33554432,3,[[4,-42,[0,"9cQfNzmFZNIaJzAbwsxSWP"],[5,20,10]],[2,-43,[0,"2eCmRcJolMiYxyHYOEbhCR"],10]],[1,"b9unig07VCzKuy02PZQgSX",null,null,null,1,0],[1,13.052,23.493,0]],[3,"meimao-1",33554432,3,[[4,-44,[0,"afwTXR1qVFoKAOoW4NurYQ"],[5,20,10]],[2,-45,[0,"1ec8X1KvlL8LquaXHbqVf0"],11]],[1,"b9MAWmxwpIvYU9wyVMh4k0",null,null,null,1,0],[1,-9.92,25.581,0]],[3,"yanjing-2",33554432,3,[[4,-46,[0,"7coysbxAJDF6rzLJewN/2y"],[5,7,7]],[2,-47,[0,"226lu+ve5AuJGATsrwkwkg"],12]],[1,"d6sHNtNMdGUI8MBI8v00fO",null,null,null,1,0],[1,13.574,6.787,0]],[3,"yanjing-1",33554432,3,[[4,-48,[0,"d2uIGk9adFzYono4ZdkHAr"],[5,7,7]],[2,-49,[0,"3blgG0AE5FxaRxBpeMPu8t"],13]],[1,"541T3cQD1G86fYIPQeFH4X",null,null,null,1,0],[1,-14.095,10.963,0]]],0,[0,3,1,0,0,1,0,0,1,0,-1,4,0,-2,2,0,0,2,0,-1,5,0,-2,6,0,-3,7,0,-4,8,0,-5,9,0,-6,10,0,-7,3,0,0,3,0,-1,11,0,-2,12,0,-3,13,0,-4,14,0,-5,15,0,-6,16,0,-7,17,0,0,4,0,0,4,0,0,5,0,0,5,0,0,6,0,0,6,0,0,7,0,0,7,0,0,8,0,0,8,0,0,9,0,0,9,0,0,10,0,0,10,0,0,11,0,0,11,0,0,12,0,0,12,0,0,13,0,0,13,0,0,14,0,0,14,0,0,15,0,0,15,0,0,16,0,0,16,0,0,17,0,0,17,0,4,1,49],[0,0,0,0,0,0,0,0,0,0,0,0,0,0,0,0],[1,1,1,1,1,1,1,1,1,1,1,1,1,1,-1,5],[7,0,8,0,9,0,0,1,1,10,11,12,2,2,3,3]],[[{"name":"icon-02","rect":{"x":0,"y":0,"width":134,"height":28},"offset":{"x":0,"y":0},"originalSize":{"width":134,"height":28},"rotated":false,"capInsets":[0,0,0,0],"vertices":{"rawPosition":[-67,-14,0,67,-14,0,-67,14,0,67,14,0],"indexes":[0,1,2,2,1,3],"uv":[0,28,134,28,0,0,134,0],"nuv":[0,0,1,0,0,1,1,1],"minPos":{"x":-67,"y":-14,"z":0},"maxPos":{"x":67,"y":14,"z":0}},"packable":true,"pixelsToUnit":100,"pivot":{"x":0.5,"y":0.5},"meshType":0}],[0],0,[0],[2],[13]],[[{"name":"icon-05","rect":{"x":0,"y":0,"width":18,"height":31},"offset":{"x":0,"y":0},"originalSize":{"width":18,"height":31},"rotated":false,"capInsets":[0,0,0,0],"vertices":{"rawPosition":[-9,-15.5,0,9,-15.5,0,-9,15.5,0,9,15.5,0],"indexes":[0,1,2,2,1,3],"uv":[0,31,18,31,0,0,18,0],"nuv":[0,0,1,0,0,1,1,1],"minPos":{"x":-9,"y":-15.5,"z":0},"maxPos":{"x":9,"y":15.5,"z":0}},"packable":true,"pixelsToUnit":100,"pivot":{"x":0.5,"y":0.5},"meshType":0}],[0],0,[0],[2],[14]],[[{"name":"icon-03","rect":{"x":0,"y":0,"width":59,"height":80},"offset":{"x":0,"y":0},"originalSize":{"width":59,"height":80},"rotated":false,"capInsets":[0,0,0,0],"vertices":{"rawPosition":[-29.5,-40,0,29.5,-40,0,-29.5,40,0,29.5,40,0],"indexes":[0,1,2,2,1,3],"uv":[0,80,59,80,0,0,59,0],"nuv":[0,0,1,0,0,1,1,1],"minPos":{"x":-29.5,"y":-40,"z":0},"maxPos":{"x":29.5,"y":40,"z":0}},"packable":true,"pixelsToUnit":100,"pivot":{"x":0.5,"y":0.5},"meshType":0}],[0],0,[0],[2],[15]],[[{"name":"icon-06","rect":{"x":0,"y":0,"width":7,"height":7},"offset":{"x":0,"y":0},"originalSize":{"width":7,"height":7},"rotated":false,"capInsets":[0,0,0,0],"vertices":{"rawPosition":[-3.5,-3.5,0,3.5,-3.5,0,-3.5,3.5,0,3.5,3.5,0],"indexes":[0,1,2,2,1,3],"uv":[0,7,7,7,0,0,7,0],"nuv":[0,0,1,0,0,1,1,1],"minPos":{"x":-3.5,"y":-3.5,"z":0},"maxPos":{"x":3.5,"y":3.5,"z":0}},"packable":true,"pixelsToUnit":100,"pivot":{"x":0.5,"y":0.5},"meshType":0}],[0],0,[0],[2],[16]],[[{"name":"icon-07","rect":{"x":0,"y":0,"width":29,"height":46},"offset":{"x":0,"y":0},"originalSize":{"width":29,"height":46},"rotated":false,"capInsets":[0,0,0,0],"vertices":{"rawPosition":[-14.5,-23,0,14.5,-23,0,-14.5,23,0,14.5,23,0],"indexes":[0,1,2,2,1,3],"uv":[0,46,29,46,0,0,29,0],"nuv":[0,0,1,0,0,1,1,1],"minPos":{"x":-14.5,"y":-23,"z":0},"maxPos":{"x":14.5,"y":23,"z":0}},"packable":true,"pixelsToUnit":100,"pivot":{"x":0.5,"y":0.5},"meshType":0}],[0],0,[0],[2],[17]],[[{"name":"icon-01","rect":{"x":0,"y":0,"width":139,"height":106},"offset":{"x":0,"y":0},"originalSize":{"width":139,"height":106},"rotated":false,"capInsets":[0,0,0,0],"vertices":{"rawPosition":[-69.5,-53,0,69.5,-53,0,-69.5,53,0,69.5,53,0],"indexes":[0,1,2,2,1,3],"uv":[0,106,139,106,0,0,139,0],"nuv":[0,0,1,0,0,1,1,1],"minPos":{"x":-69.5,"y":-53,"z":0},"maxPos":{"x":69.5,"y":53,"z":0}},"packable":true,"pixelsToUnit":100,"pivot":{"x":0.5,"y":0.5},"meshType":0}],[0],0,[0],[2],[18]]]]
